stntrading/__init__.py
stntrading/enums.py
stntrading/exceptions.py
stntrading/stn.py
stntrading-1.1.0.dist-info/LICENSE
stntrading-1.1.0.dist-info/METADATA
stntrading-1.1.0.dist-info/WHEEL
stntrading-1.1.0.dist-info/top_level.txt
stntrading-1.1.0.dist-info/RECORD
