Metadata-Version: 2.1
Name: stntrading
Version: 1.1.0
Summary: Interact with STNTrading's API
Author-email: offish <overutilization@gmail.com>
Project-URL: Homepage, https://github.com/offish/stntrading
Project-URL: Bug Tracker, https://github.com/offish/stntrading/issues
Keywords: tf2,stntrading,stn
Classifier: Programming Language :: Python :: 3
Classifier: License :: OSI Approved :: MIT License
Classifier: Operating System :: OS Independent
Requires-Python: >=3.10
License-File: LICENSE
Requires-Dist: requests
